.editorconfig
CHANGES.rst
MANIFEST.in
README.rst
bootstrap.py
buildout.cfg
setup.py
src/ps/__init__.py
src/ps.releaser.egg-info/PKG-INFO
src/ps.releaser.egg-info/SOURCES.txt
src/ps.releaser.egg-info/dependency_links.txt
src/ps.releaser.egg-info/entry_points.txt
src/ps.releaser.egg-info/namespace_packages.txt
src/ps.releaser.egg-info/not-zip-safe
src/ps.releaser.egg-info/requires.txt
src/ps.releaser.egg-info/top_level.txt
src/ps/releaser/__init__.py
src/ps/releaser/diazo.py