Metadata-Version: 1.1
Name: ps.releaser
Version: 0.3
Summary: Plugins for release automation with zest.releaser.
Home-page: https://github.com/propertyshelf/ps.releaser
Author: Propertyshelf, Inc.
Author-email: development@propertyshelf.com
License: BSD
Download-URL: http://pypi.python.org/pypi/ps.releaser
Platform: UNKNOWN
Classifier: Environment :: Console
Classifier: Intended Audience :: Developers
Classifier: License :: OSI Approved :: BSD License
Classifier: Natural Language :: English
Classifier: Operating System :: OS Independent
Classifier: Programming Language :: Python
Classifier: Topic :: Software Development :: Code Generators
Classifier: Topic :: Utilities
